MANIFEST.in
README.rst
setup.py
django_documentation.egg-info/PKG-INFO
django_documentation.egg-info/SOURCES.txt
django_documentation.egg-info/dependency_links.txt
django_documentation.egg-info/requires.txt
django_documentation.egg-info/top_level.txt
documentation/__init__.py
documentation/app_settings.py
documentation/models.py
documentation/tests.py
documentation/urls.py
documentation/views.py
documentation/management/__init__.py
documentation/management/commands/__init__.py
documentation/management/commands/makedoc.py
example_documentation/__init__.py
example_documentation/manage.py
example_documentation/settings.py
example_documentation/urls.py