Metadata-Version: 1.0
Name: django-documentation
Version: 1.0
Summary: Provides a way to integrate a protected sphinx based
Home-page: http://github.com/Narsil/django-documentation
Author: Nicolas Patry
Author-email: nicolas@kwyk.fr
License: UNKNOWN
Download-URL: http://github.com/Narsil/django-documentation
Keywords: django documentation sphinx authentification
Platform: UNKNOWN
Classifier: Development Status :: 4 - Beta
Classifier: Intended Audience :: Developers
Classifier: License :: OSI Approved :: GNU Library or Lesser General Public License (LGPL)
Classifier: Topic :: Software Development :: Libraries :: Python Modules
Classifier: Environment :: Web Environment
Classifier: Topic :: Internet
Classifier: Operating System :: OS Independent
Classifier: Programming Language :: Python
Classifier: Framework :: Django
